<proposicoes>
  <proposicao>
    <id>562600</id>
    <nome>CAE 2/2012 CMO =&gt; PLN 24/2012 CN</nome>
    <tipoProposicao>
      <id>685</id>
      <sigla>CAE</sigla>
      <nome>Relatório</nome>
    </tipoProposicao>
    <numero>2</numero>
    <ano>2012</ano>
    <orgaoNumerador>
      <id>6855</id>
      <sigla>CMO       </sigla>
      <nome>Comissão Mista de Planos, Orçamentos Públicos e Fiscalização</nome>
    </orgaoNumerador>
    <datApresentacao>11/12/2012 21:16:00</datApresentacao>
    <txtEmenta> Relatório do Comitê de Admissibilidade de Emendas sobre o Exame de Admissibilidade das emendas coletivas (Bancada e Comissão) apresentadas ao PLN 24/2012 - Projeto de Lei Orçamentária para 2013.</txtEmenta>
    <txtExplicacaoEmenta>
    </txtExplicacaoEmenta>
    <regime>
      <codRegime>99</codRegime>
      <txtRegime>.</txtRegime>
    </regime>
    <apreciacao>
      <id>99</id>
      <txtApreciacao>.</txtApreciacao>
    </apreciacao>
    <autor1>
      <txtNomeAutor>Marcus Pestana</txtNomeAutor>
      <idecadastro>159238</idecadastro>
      <codPartido>128</codPartido>
      <txtSiglaPartido>PSDB      </txtSiglaPartido>
      <txtSiglaUF>MG</txtSiglaUF>
    </autor1>
    <qtdAutores>1</qtdAutores>
    <ultimoDespacho>
      <datDespacho>
      </datDespacho>
      <txtDespacho>
      </txtDespacho>
    </ultimoDespacho>
    <situacao>
      <id>923</id>
      <descricao>Arquivada</descricao>
      <orgao>
        <codOrgaoEstado>6855</codOrgaoEstado>
        <siglaOrgaoEstado>CMO       </siglaOrgaoEstado>
      </orgao>
      <principal>
        <codProposicaoPrincipal>0</codProposicaoPrincipal>
        <proposicaoPrincipal>
        </proposicaoPrincipal>
      </principal>
    </situacao>
    <indGenero>o</indGenero>
    <qtdOrgaosComEstado>1</qtdOrgaosComEstado>
  </proposicao>
  <proposicao>
    <id>561942</id>
    <nome>CAE 1/2012 CMO =&gt; PLN 24/2012 CN</nome>
    <tipoProposicao>
      <id>681</id>
      <sigla>CAE</sigla>
      <nome>Relatório de Atividades do Comitê de Admissibilidade de Emendas (CAE)</nome>
    </tipoProposicao>
    <numero>1</numero>
    <ano>2012</ano>
    <orgaoNumerador>
      <id>6855</id>
      <sigla>CMO       </sigla>
      <nome>Comissão Mista de Planos, Orçamentos Públicos e Fiscalização</nome>
    </orgaoNumerador>
    <datApresentacao>21/11/2012 11:39:00</datApresentacao>
    <txtEmenta>sobre Diretrizes e Orientações para a análise da admissibilidade de emendas ao Projeto de Lei Orçamentária para 2013, apresentado ao Projeto de Lei nº 24/2012-CN, que "Estima a receita e fixa a despesa da União para o exercício financeiro de 2013", em razão do art. 25 da Resolução nº 1/2006-CN.
Coordenador do CAE: Deputado Marcus Pestana
</txtEmenta>
    <txtExplicacaoEmenta>
    </txtExplicacaoEmenta>
    <regime>
      <codRegime>99</codRegime>
      <txtRegime>.</txtRegime>
    </regime>
    <apreciacao>
      <id>99</id>
      <txtApreciacao>.</txtApreciacao>
    </apreciacao>
    <autor1>
      <txtNomeAutor>Marcus Pestana</txtNomeAutor>
      <idecadastro>159238</idecadastro>
      <codPartido>128</codPartido>
      <txtSiglaPartido>PSDB      </txtSiglaPartido>
      <txtSiglaUF>MG</txtSiglaUF>
    </autor1>
    <qtdAutores>1</qtdAutores>
    <ultimoDespacho>
      <datDespacho>
      </datDespacho>
      <txtDespacho>
      </txtDespacho>
    </ultimoDespacho>
    <situacao>
      <id>923</id>
      <descricao>Arquivada</descricao>
      <orgao>
        <codOrgaoEstado>6855</codOrgaoEstado>
        <siglaOrgaoEstado>CMO       </siglaOrgaoEstado>
      </orgao>
      <principal>
        <codProposicaoPrincipal>0</codProposicaoPrincipal>
        <proposicaoPrincipal>
        </proposicaoPrincipal>
      </principal>
    </situacao>
    <indGenero>o</indGenero>
    <qtdOrgaosComEstado>1</qtdOrgaosComEstado>
  </proposicao>
</proposicoes>
