<?xml version="1.0" encoding="utf-8"?>
<proposicoes>
  <proposicao>
    <id>618587</id>
    <nome>MPV 649/2014</nome>
    <tipoProposicao>
      <id>291</id>
      <sigla>MPV</sigla>
      <nome>Medida Provisória</nome>
    </tipoProposicao>
    <numero>649</numero>
    <ano>2014</ano>
    <orgaoNumerador>
      <id>180</id>
      <sigla>PLEN      </sigla>
      <nome>PLENÁRIO</nome>
    </orgaoNumerador>
    <datApresentacao>6/6/2014 09:31:00</datApresentacao>
    <txtEmenta>Altera a Lei nº 12.741, de 8 de dezembro de 2012, que dispõe sobre as medidas de esclarecimento ao consumidor quanto à carga tributária incidente sobre mercadorias e serviços.</txtEmenta>
    <txtExplicacaoEmenta>
    </txtExplicacaoEmenta>
    <regime>
      <codRegime>15</codRegime>
      <txtRegime>Urgência</txtRegime>
    </regime>
    <apreciacao>
      <id>5</id>
      <txtApreciacao>Proposição Sujeita à Apreciação do Plenário</txtApreciacao>
    </apreciacao>
    <autor1>
      <txtNomeAutor>Poder Executivo</txtNomeAutor>
      <idecadastro>
      </idecadastro>
      <codPartido>
      </codPartido>
      <txtSiglaPartido>
      </txtSiglaPartido>
      <txtSiglaUF>
      </txtSiglaUF>
    </autor1>
    <qtdAutores>1</qtdAutores>
    <ultimoDespacho>
      <datDespacho>
      </datDespacho>
      <txtDespacho>
      </txtDespacho>
    </ultimoDespacho>
    <situacao>
      <id>917</id>
      <descricao>Aguardando Recebimento</descricao>
      <orgao>
        <codOrgaoEstado>4</codOrgaoEstado>
        <siglaOrgaoEstado>MESA      </siglaOrgaoEstado>
      </orgao>
      <principal>
        <codProposicaoPrincipal>0</codProposicaoPrincipal>
        <proposicaoPrincipal>
        </proposicaoPrincipal>
      </principal>
    </situacao>
    <indGenero>a</indGenero>
    <qtdOrgaosComEstado>1</qtdOrgaosComEstado>
  </proposicao>
  <proposicao>
    <id>618090</id>
    <nome>MPV 648/2014</nome>
    <tipoProposicao>
      <id>291</id>
      <sigla>MPV</sigla>
      <nome>Medida Provisória</nome>
    </tipoProposicao>
    <numero>648</numero>
    <ano>2014</ano>
    <orgaoNumerador>
      <id>180</id>
      <sigla>PLEN      </sigla>
      <nome>PLENÁRIO</nome>
    </orgaoNumerador>
    <datApresentacao>4/6/2014 09:02:00</datApresentacao>
    <txtEmenta>Altera a Lei nº 4.117, de 27 de agosto de 1962, e dispõe sobre a flexibilização do horário de transmissão do programa oficial de informações dos Poderes da República, durante a Copa do Mundo FIFA 2014.</txtEmenta>
    <txtExplicacaoEmenta>
    </txtExplicacaoEmenta>
    <regime>
      <codRegime>15</codRegime>
      <txtRegime>Urgência</txtRegime>
    </regime>
    <apreciacao>
      <id>5</id>
      <txtApreciacao>Proposição Sujeita à Apreciação do Plenário</txtApreciacao>
    </apreciacao>
    <autor1>
      <txtNomeAutor>Poder Executivo</txtNomeAutor>
      <idecadastro>
      </idecadastro>
      <codPartido>
      </codPartido>
      <txtSiglaPartido>
      </txtSiglaPartido>
      <txtSiglaUF>
      </txtSiglaUF>
    </autor1>
    <qtdAutores>1</qtdAutores>
    <ultimoDespacho>
      <datDespacho>
      </datDespacho>
      <txtDespacho>
      </txtDespacho>
    </ultimoDespacho>
    <situacao>
      <id>917</id>
      <descricao>Aguardando Recebimento</descricao>
      <orgao>
        <codOrgaoEstado>4</codOrgaoEstado>
        <siglaOrgaoEstado>MESA      </siglaOrgaoEstado>
      </orgao>
      <principal>
        <codProposicaoPrincipal>0</codProposicaoPrincipal>
        <proposicaoPrincipal>
        </proposicaoPrincipal>
      </principal>
    </situacao>
    <indGenero>a</indGenero>
    <qtdOrgaosComEstado>1</qtdOrgaosComEstado>
  </proposicao>
  <proposicao>
    <id>617512</id>
    <nome>MPV 647/2014</nome>
    <tipoProposicao>
      <id>291</id>
      <sigla>MPV</sigla>
      <nome>Medida Provisória</nome>
    </tipoProposicao>
    <numero>647</numero>
    <ano>2014</ano>
    <orgaoNumerador>
      <id>180</id>
      <sigla>PLEN      </sigla>
      <nome>PLENÁRIO</nome>
    </orgaoNumerador>
    <datApresentacao>29/5/2014 08:56:00</datApresentacao>
    <txtEmenta>Dispõe sobre a adição obrigatória de biodiesel ao óleo diesel comercializado ao consumidor final, e dá outras providências.</txtEmenta>
    <txtExplicacaoEmenta>
    </txtExplicacaoEmenta>
    <regime>
      <codRegime>15</codRegime>
      <txtRegime>Urgência</txtRegime>
    </regime>
    <apreciacao>
      <id>5</id>
      <txtApreciacao>Proposição Sujeita à Apreciação do Plenário</txtApreciacao>
    </apreciacao>
    <autor1>
      <txtNomeAutor>Poder Executivo</txtNomeAutor>
      <idecadastro>
      </idecadastro>
      <codPartido>
      </codPartido>
      <txtSiglaPartido>
      </txtSiglaPartido>
      <txtSiglaUF>
      </txtSiglaUF>
    </autor1>
    <qtdAutores>1</qtdAutores>
    <ultimoDespacho>
      <datDespacho>
      </datDespacho>
      <txtDespacho>
      </txtDespacho>
    </ultimoDespacho>
    <situacao>
      <id>917</id>
      <descricao>Aguardando Recebimento</descricao>
      <orgao>
        <codOrgaoEstado>4</codOrgaoEstado>
        <siglaOrgaoEstado>MESA      </siglaOrgaoEstado>
      </orgao>
      <principal>
        <codProposicaoPrincipal>0</codProposicaoPrincipal>
        <proposicaoPrincipal>
        </proposicaoPrincipal>
      </principal>
    </situacao>
    <indGenero>a</indGenero>
    <qtdOrgaosComEstado>1</qtdOrgaosComEstado>
  </proposicao>
  <proposicao>
    <id>616955</id>
    <nome>MPV 646/2014</nome>
    <tipoProposicao>
      <id>291</id>
      <sigla>MPV</sigla>
      <nome>Medida Provisória</nome>
    </tipoProposicao>
    <numero>646</numero>
    <ano>2014</ano>
    <orgaoNumerador>
      <id>180</id>
      <sigla>PLEN      </sigla>
      <nome>PLENÁRIO</nome>
    </orgaoNumerador>
    <datApresentacao>27/5/2014 09:08:00</datApresentacao>
    <txtEmenta>Altera a Lei nº 9.503, de 23 de setembro de 1997, que institui o Código de Trânsito Brasileiro.</txtEmenta>
    <txtExplicacaoEmenta>Trata da identificação, registro e licenciamento para o trânsito em via pública de tratores destinados a executar 
destinados a puxar ou arrastar maquinaria de qualquer natureza ou a executar trabalhos agrícolas e de construção ou de pavimentação.</txtExplicacaoEmenta>
    <regime>
      <codRegime>15</codRegime>
      <txtRegime>Urgência</txtRegime>
    </regime>
    <apreciacao>
      <id>5</id>
      <txtApreciacao>Proposição Sujeita à Apreciação do Plenário</txtApreciacao>
    </apreciacao>
    <autor1>
      <txtNomeAutor>Poder Executivo</txtNomeAutor>
      <idecadastro>
      </idecadastro>
      <codPartido>
      </codPartido>
      <txtSiglaPartido>
      </txtSiglaPartido>
      <txtSiglaUF>
      </txtSiglaUF>
    </autor1>
    <qtdAutores>1</qtdAutores>
    <ultimoDespacho>
      <datDespacho>
      </datDespacho>
      <txtDespacho>
      </txtDespacho>
    </ultimoDespacho>
    <situacao>
      <id>917</id>
      <descricao>Aguardando Recebimento</descricao>
      <orgao>
        <codOrgaoEstado>4</codOrgaoEstado>
        <siglaOrgaoEstado>MESA      </siglaOrgaoEstado>
      </orgao>
      <principal>
        <codProposicaoPrincipal>0</codProposicaoPrincipal>
        <proposicaoPrincipal>
        </proposicaoPrincipal>
      </principal>
    </situacao>
    <indGenero>a</indGenero>
    <qtdOrgaosComEstado>1</qtdOrgaosComEstado>
  </proposicao>
  <proposicao>
    <id>614009</id>
    <nome>MPV 645/2014</nome>
    <tipoProposicao>
      <id>291</id>
      <sigla>MPV</sigla>
      <nome>Medida Provisória</nome>
    </tipoProposicao>
    <numero>645</numero>
    <ano>2014</ano>
    <orgaoNumerador>
      <id>180</id>
      <sigla>PLEN      </sigla>
      <nome>PLENÁRIO</nome>
    </orgaoNumerador>
    <datApresentacao>6/5/2014 09:41:00</datApresentacao>
    <txtEmenta>Dispõe sobre a ampliação do Auxílio Emergencial Financeiro relativo aos desastres ocorridos em 2012.</txtEmenta>
    <txtExplicacaoEmenta>
    </txtExplicacaoEmenta>
    <regime>
      <codRegime>15</codRegime>
      <txtRegime>Urgência</txtRegime>
    </regime>
    <apreciacao>
      <id>5</id>
      <txtApreciacao>Proposição Sujeita à Apreciação do Plenário</txtApreciacao>
    </apreciacao>
    <autor1>
      <txtNomeAutor>Poder Executivo</txtNomeAutor>
      <idecadastro>
      </idecadastro>
      <codPartido>
      </codPartido>
      <txtSiglaPartido>
      </txtSiglaPartido>
      <txtSiglaUF>
      </txtSiglaUF>
    </autor1>
    <qtdAutores>1</qtdAutores>
    <ultimoDespacho>
      <datDespacho>
      </datDespacho>
      <txtDespacho>
      </txtDespacho>
    </ultimoDespacho>
    <situacao>
      <id>917</id>
      <descricao>Aguardando Recebimento</descricao>
      <orgao>
        <codOrgaoEstado>4</codOrgaoEstado>
        <siglaOrgaoEstado>MESA      </siglaOrgaoEstado>
      </orgao>
      <principal>
        <codProposicaoPrincipal>0</codProposicaoPrincipal>
        <proposicaoPrincipal>
        </proposicaoPrincipal>
      </principal>
    </situacao>
    <indGenero>a</indGenero>
    <qtdOrgaosComEstado>1</qtdOrgaosComEstado>
  </proposicao>
  <proposicao>
    <id>613960</id>
    <nome>MPV 644/2014</nome>
    <tipoProposicao>
      <id>291</id>
      <sigla>MPV</sigla>
      <nome>Medida Provisória</nome>
    </tipoProposicao>
    <numero>644</numero>
    <ano>2014</ano>
    <orgaoNumerador>
      <id>180</id>
      <sigla>PLEN      </sigla>
      <nome>PLENÁRIO</nome>
    </orgaoNumerador>
    <datApresentacao>2/5/2014 09:35:00</datApresentacao>
    <txtEmenta>Altera os valores da tabela do imposto sobre a renda da pessoa física; altera a Lei nº 7.713, de 22 de dezembro de 1988, a Lei nº 9.250, de 26 de dezembro de 1995, e a Lei nº 11.482, de 31 de maio de 2007.</txtEmenta>
    <txtExplicacaoEmenta>
    </txtExplicacaoEmenta>
    <regime>
      <codRegime>15</codRegime>
      <txtRegime>Urgência</txtRegime>
    </regime>
    <apreciacao>
      <id>5</id>
      <txtApreciacao>Proposição Sujeita à Apreciação do Plenário</txtApreciacao>
    </apreciacao>
    <autor1>
      <txtNomeAutor>Poder Executivo</txtNomeAutor>
      <idecadastro>
      </idecadastro>
      <codPartido>
      </codPartido>
      <txtSiglaPartido>
      </txtSiglaPartido>
      <txtSiglaUF>
      </txtSiglaUF>
    </autor1>
    <qtdAutores>1</qtdAutores>
    <ultimoDespacho>
      <datDespacho>
      </datDespacho>
      <txtDespacho>
      </txtDespacho>
    </ultimoDespacho>
    <situacao>
      <id>917</id>
      <descricao>Aguardando Recebimento</descricao>
      <orgao>
        <codOrgaoEstado>4</codOrgaoEstado>
        <siglaOrgaoEstado>MESA      </siglaOrgaoEstado>
      </orgao>
      <principal>
        <codProposicaoPrincipal>0</codProposicaoPrincipal>
        <proposicaoPrincipal>
        </proposicaoPrincipal>
      </principal>
    </situacao>
    <indGenero>a</indGenero>
    <qtdOrgaosComEstado>1</qtdOrgaosComEstado>
  </proposicao>
  <proposicao>
    <id>613497</id>
    <nome>MPV 643/2014</nome>
    <tipoProposicao>
      <id>291</id>
      <sigla>MPV</sigla>
      <nome>Medida Provisória</nome>
    </tipoProposicao>
    <numero>643</numero>
    <ano>2014</ano>
    <orgaoNumerador>
      <id>180</id>
      <sigla>PLEN      </sigla>
      <nome>PLENÁRIO</nome>
    </orgaoNumerador>
    <datApresentacao>25/4/2014 09:24:00</datApresentacao>
    <txtEmenta>Altera a Lei nº 9.648, de 27 de maio de 1998, para dispor sobre o mandato de Diretor-Geral do Operador Nacional do Sistema Elétrico - ONS.</txtEmenta>
    <txtExplicacaoEmenta>
    </txtExplicacaoEmenta>
    <regime>
      <codRegime>15</codRegime>
      <txtRegime>Urgência</txtRegime>
    </regime>
    <apreciacao>
      <id>5</id>
      <txtApreciacao>Proposição Sujeita à Apreciação do Plenário</txtApreciacao>
    </apreciacao>
    <autor1>
      <txtNomeAutor>Poder Executivo</txtNomeAutor>
      <idecadastro>
      </idecadastro>
      <codPartido>
      </codPartido>
      <txtSiglaPartido>
      </txtSiglaPartido>
      <txtSiglaUF>
      </txtSiglaUF>
    </autor1>
    <qtdAutores>1</qtdAutores>
    <ultimoDespacho>
      <datDespacho>
      </datDespacho>
      <txtDespacho>
      </txtDespacho>
    </ultimoDespacho>
    <situacao>
      <id>917</id>
      <descricao>Aguardando Recebimento</descricao>
      <orgao>
        <codOrgaoEstado>4</codOrgaoEstado>
        <siglaOrgaoEstado>MESA      </siglaOrgaoEstado>
      </orgao>
      <principal>
        <codProposicaoPrincipal>0</codProposicaoPrincipal>
        <proposicaoPrincipal>
        </proposicaoPrincipal>
      </principal>
    </situacao>
    <indGenero>a</indGenero>
    <qtdOrgaosComEstado>1</qtdOrgaosComEstado>
  </proposicao>
  <proposicao>
    <id>612875</id>
    <nome>MPV 642/2014</nome>
    <tipoProposicao>
      <id>291</id>
      <sigla>MPV</sigla>
      <nome>Medida Provisória</nome>
    </tipoProposicao>
    <numero>642</numero>
    <ano>2014</ano>
    <orgaoNumerador>
      <id>180</id>
      <sigla>PLEN      </sigla>
      <nome>PLENÁRIO</nome>
    </orgaoNumerador>
    <datApresentacao>22/4/2014 10:47:00</datApresentacao>
    <txtEmenta>Abre crédito extraordinário, em favor do Ministério da Defesa e de Operações Oficiais de Crédito, no valor de R$ 5.100.000.000,00, para os fins que especifica.</txtEmenta>
    <txtExplicacaoEmenta>Abre crédito extraordinário para apoio logístico às Forças de Segurança Pública do Estado do Rio de Janeiro e para o Fundo de Financiamento ao Estudante do Ensino Superior. </txtExplicacaoEmenta>
    <regime>
      <codRegime>15</codRegime>
      <txtRegime>Urgência</txtRegime>
    </regime>
    <apreciacao>
      <id>5</id>
      <txtApreciacao>Proposição Sujeita à Apreciação do Plenário</txtApreciacao>
    </apreciacao>
    <autor1>
      <txtNomeAutor>Poder Executivo</txtNomeAutor>
      <idecadastro>
      </idecadastro>
      <codPartido>
      </codPartido>
      <txtSiglaPartido>
      </txtSiglaPartido>
      <txtSiglaUF>
      </txtSiglaUF>
    </autor1>
    <qtdAutores>1</qtdAutores>
    <ultimoDespacho>
      <datDespacho>
      </datDespacho>
      <txtDespacho>
      </txtDespacho>
    </ultimoDespacho>
    <situacao>
      <id>926</id>
      <descricao>Aguardando Retorno </descricao>
      <orgao>
        <codOrgaoEstado>4</codOrgaoEstado>
        <siglaOrgaoEstado>MESA      </siglaOrgaoEstado>
      </orgao>
      <principal>
        <codProposicaoPrincipal>0</codProposicaoPrincipal>
        <proposicaoPrincipal>
        </proposicaoPrincipal>
      </principal>
    </situacao>
    <indGenero>a</indGenero>
    <qtdOrgaosComEstado>1</qtdOrgaosComEstado>
  </proposicao>
  <proposicao>
    <id>609200</id>
    <nome>MPV 641/2014</nome>
    <tipoProposicao>
      <id>291</id>
      <sigla>MPV</sigla>
      <nome>Medida Provisória</nome>
    </tipoProposicao>
    <numero>641</numero>
    <ano>2014</ano>
    <orgaoNumerador>
      <id>180</id>
      <sigla>PLEN      </sigla>
      <nome>PLENÁRIO</nome>
    </orgaoNumerador>
    <datApresentacao>24/3/2014 14:20:00</datApresentacao>
    <txtEmenta>Altera a Lei nº 10.848, de 15 de março de 2004, que dispõe sobre a comercialização de energia elétrica.</txtEmenta>
    <txtExplicacaoEmenta>
    </txtExplicacaoEmenta>
    <regime>
      <codRegime>15</codRegime>
      <txtRegime>Urgência</txtRegime>
    </regime>
    <apreciacao>
      <id>5</id>
      <txtApreciacao>Proposição Sujeita à Apreciação do Plenário</txtApreciacao>
    </apreciacao>
    <autor1>
      <txtNomeAutor>Poder Executivo</txtNomeAutor>
      <idecadastro>
      </idecadastro>
      <codPartido>
      </codPartido>
      <txtSiglaPartido>
      </txtSiglaPartido>
      <txtSiglaUF>
      </txtSiglaUF>
    </autor1>
    <qtdAutores>1</qtdAutores>
    <ultimoDespacho>
      <datDespacho>
      </datDespacho>
      <txtDespacho>
      </txtDespacho>
    </ultimoDespacho>
    <situacao>
      <id>917</id>
      <descricao>Aguardando Recebimento</descricao>
      <orgao>
        <codOrgaoEstado>4</codOrgaoEstado>
        <siglaOrgaoEstado>MESA      </siglaOrgaoEstado>
      </orgao>
      <principal>
        <codProposicaoPrincipal>0</codProposicaoPrincipal>
        <proposicaoPrincipal>
        </proposicaoPrincipal>
      </principal>
    </situacao>
    <indGenero>a</indGenero>
    <qtdOrgaosComEstado>1</qtdOrgaosComEstado>
  </proposicao>
  <proposicao>
    <id>609196</id>
    <nome>MPV 639/2014</nome>
    <tipoProposicao>
      <id>291</id>
      <sigla>MPV</sigla>
      <nome>Medida Provisória</nome>
    </tipoProposicao>
    <numero>639</numero>
    <ano>2014</ano>
    <orgaoNumerador>
      <id>180</id>
      <sigla>PLEN      </sigla>
      <nome>PLENÁRIO</nome>
    </orgaoNumerador>
    <datApresentacao>21/3/2014 14:20:00</datApresentacao>
    <txtEmenta>Autoriza o Banco Central do Brasil a alienar à Companhia de Desenvolvimento Urbano da Região do Porto do Rio de Janeiro S.A. - CDURP os imóveis que especifica.</txtEmenta>
    <txtExplicacaoEmenta>
    </txtExplicacaoEmenta>
    <regime>
      <codRegime>15</codRegime>
      <txtRegime>Urgência</txtRegime>
    </regime>
    <apreciacao>
      <id>5</id>
      <txtApreciacao>Proposição Sujeita à Apreciação do Plenário</txtApreciacao>
    </apreciacao>
    <autor1>
      <txtNomeAutor>Poder Executivo</txtNomeAutor>
      <idecadastro>
      </idecadastro>
      <codPartido>
      </codPartido>
      <txtSiglaPartido>
      </txtSiglaPartido>
      <txtSiglaUF>
      </txtSiglaUF>
    </autor1>
    <qtdAutores>1</qtdAutores>
    <ultimoDespacho>
      <datDespacho>
      </datDespacho>
      <txtDespacho>
      </txtDespacho>
    </ultimoDespacho>
    <situacao>
      <id>926</id>
      <descricao>Aguardando Retorno </descricao>
      <orgao>
        <codOrgaoEstado>4</codOrgaoEstado>
        <siglaOrgaoEstado>MESA      </siglaOrgaoEstado>
      </orgao>
      <principal>
        <codProposicaoPrincipal>0</codProposicaoPrincipal>
        <proposicaoPrincipal>
        </proposicaoPrincipal>
      </principal>
    </situacao>
    <indGenero>a</indGenero>
    <qtdOrgaosComEstado>1</qtdOrgaosComEstado>
  </proposicao>
  <proposicao>
    <id>609198</id>
    <nome>MPV 640/2014</nome>
    <tipoProposicao>
      <id>291</id>
      <sigla>MPV</sigla>
      <nome>Medida Provisória</nome>
    </tipoProposicao>
    <numero>640</numero>
    <ano>2014</ano>
    <orgaoNumerador>
      <id>180</id>
      <sigla>PLEN      </sigla>
      <nome>PLENÁRIO</nome>
    </orgaoNumerador>
    <datApresentacao>21/3/2014 14:20:00</datApresentacao>
    <txtEmenta>Cria, em caráter temporário, as Funções Comissionadas de Grandes Eventos - FCGE e extingue Funções Comissionadas Técnicas - FCT.</txtEmenta>
    <txtExplicacaoEmenta>
    </txtExplicacaoEmenta>
    <regime>
      <codRegime>15</codRegime>
      <txtRegime>Urgência</txtRegime>
    </regime>
    <apreciacao>
      <id>5</id>
      <txtApreciacao>Proposição Sujeita à Apreciação do Plenário</txtApreciacao>
    </apreciacao>
    <autor1>
      <txtNomeAutor>Poder Executivo</txtNomeAutor>
      <idecadastro>
      </idecadastro>
      <codPartido>
      </codPartido>
      <txtSiglaPartido>
      </txtSiglaPartido>
      <txtSiglaUF>
      </txtSiglaUF>
    </autor1>
    <qtdAutores>1</qtdAutores>
    <ultimoDespacho>
      <datDespacho>
      </datDespacho>
      <txtDespacho>
      </txtDespacho>
    </ultimoDespacho>
    <situacao>
      <id>926</id>
      <descricao>Aguardando Retorno </descricao>
      <orgao>
        <codOrgaoEstado>4</codOrgaoEstado>
        <siglaOrgaoEstado>MESA      </siglaOrgaoEstado>
      </orgao>
      <principal>
        <codProposicaoPrincipal>0</codProposicaoPrincipal>
        <proposicaoPrincipal>
        </proposicaoPrincipal>
      </principal>
    </situacao>
    <indGenero>a</indGenero>
    <qtdOrgaosComEstado>1</qtdOrgaosComEstado>
  </proposicao>
  <proposicao>
    <id>605355</id>
    <nome>MPV 638/2014</nome>
    <tipoProposicao>
      <id>291</id>
      <sigla>MPV</sigla>
      <nome>Medida Provisória</nome>
    </tipoProposicao>
    <numero>638</numero>
    <ano>2014</ano>
    <orgaoNumerador>
      <id>180</id>
      <sigla>PLEN      </sigla>
      <nome>PLENÁRIO</nome>
    </orgaoNumerador>
    <datApresentacao>20/1/2014 11:05:00</datApresentacao>
    <txtEmenta>Altera a Lei nº 12.715, de 17 de setembro de 2012, que institui o Programa de Incentivo à Inovação Tecnológica e Adensamento da Cadeia Produtiva de Veículos Automotores - Inovar-Auto.

NOVA EMENTA: Altera as Leis nºs 12.715, de 17 de setembro de 2012, que institui o Programa de Incentivo à Inovação Tecnológica e Adensamento da Cadeia Produtiva de Veículos Automotores - INOVAR-AUTO, 12.873, de 24 de outubro de 2013, e 10.233, de 5 de junho de 2001; e dá outras providências.</txtEmenta>
    <txtExplicacaoEmenta>Altera critérios para habilitação e cancelamento do Inovar-Auto.</txtExplicacaoEmenta>
    <regime>
      <codRegime>15</codRegime>
      <txtRegime>Urgência</txtRegime>
    </regime>
    <apreciacao>
      <id>5</id>
      <txtApreciacao>Proposição Sujeita à Apreciação do Plenário</txtApreciacao>
    </apreciacao>
    <autor1>
      <txtNomeAutor>Poder Executivo</txtNomeAutor>
      <idecadastro>
      </idecadastro>
      <codPartido>
      </codPartido>
      <txtSiglaPartido>
      </txtSiglaPartido>
      <txtSiglaUF>
      </txtSiglaUF>
    </autor1>
    <qtdAutores>1</qtdAutores>
    <ultimoDespacho>
      <datDespacho>
      </datDespacho>
      <txtDespacho>
      </txtDespacho>
    </ultimoDespacho>
    <situacao>
      <id>1140</id>
      <descricao>Transformado em Norma Jurídica</descricao>
      <orgao>
        <codOrgaoEstado>4</codOrgaoEstado>
        <siglaOrgaoEstado>MESA      </siglaOrgaoEstado>
      </orgao>
      <principal>
        <codProposicaoPrincipal>0</codProposicaoPrincipal>
        <proposicaoPrincipal>
        </proposicaoPrincipal>
      </principal>
    </situacao>
    <indGenero>a</indGenero>
    <qtdOrgaosComEstado>1</qtdOrgaosComEstado>
  </proposicao>
</proposicoes>
